web/__init__.py
web/db.py
web/exceptions.py
web/models.py
web/runner.py
web/version.py
web/api/__init__.py
web/api/errors.py
web/backup/__init__.py
web/backup/forms.py
web/backup/views.py
web/config/__init__.py
web/config/form.py
web/config/view.py
web/display/__init__.py
web/display/form.py
web/display/view.py
web/login/__init__.py
web/login/form.py
web/login/view.py
web/main/__init__.py
web/main/errors.py
web/main/form.py
web/main/view.py
web/manager/__init__.py
web/manager/form.py
web/manager/view.py
web/pitr/__init__.py
web/pitr/form.py
web/pitr/view.py
web/restore/__init__.py
web/restore/form.py
web/restore/view.py
web/schedule/__init__.py
web/schedule/form.py
web/schedule/view.py
web/static/css/style.css
web/static/images/favicon.ico
web/static/js/jquery-2.2.4.js
web/templates/403.html
web/templates/404.html
web/templates/500.html
web/templates/base.html
web/templates/index.html
web/templates/support.html
web/templates/backup/main.html
web/templates/config/login.html
web/templates/display/main.html
web/templates/login/login.html
web/templates/main/main.html
web/templates/manager/manager.html
web/templates/pitr/login.html
web/templates/restore/main.html
web/templates/schedule/login.html
web/templates/upload/main.html
web/upload/__init__.py
web/upload/form.py
web/upload/view.py
frabit_web-2.1.0.dist-info/LICENSE
frabit_web-2.1.0.dist-info/METADATA
frabit_web-2.1.0.dist-info/WHEEL
frabit_web-2.1.0.dist-info/top_level.txt
frabit_web-2.1.0.dist-info/RECORD
