Metadata-Version: 2.1
Name: frabit-web
Version: 2.1.0
Summary: A web platform used with frabit-server
Home-page: https://github.com/frabitech/frabit-web
Author: FrabiTech Limited
Author-email: blylei.info@gmail.com
License: GPL-3.0
Platform: Linux
Classifier: Framework :: Flask
Classifier: Environment :: Web Environment
Classifier: Development Status :: 4 - Beta
Classifier: Topic :: System :: Archiving :: Backup
Classifier: Topic :: Database
Classifier: Topic :: System :: Recovery Tools
Classifier: License :: OSI Approved :: GNU General Public License v3 or later (GPLv3+)
Classifier: Programming Language :: Python
Classifier: Programming Language :: Python :: 3.6
Classifier: Programming Language :: Python :: 3.7
Classifier: Programming Language :: Python :: 3.8
License-File: LICENSE
Requires-Dist: mysql-connector-python (>=8.0.22)
Requires-Dist: argh (>=0.21.2)
Requires-Dist: python-dateutil
Provides-Extra: completion
Requires-Dist: argcomplete ; extra == 'completion'
